generate_acip_schema/Elasticsearch.py
generate_acip_schema/GenerateDocument.py
generate_acip_schema/GoogleSheets.py
generate_acip_schema/__init__.py
generate_acip_schema-0.0.2.dist-info/LICENSE
generate_acip_schema-0.0.2.dist-info/METADATA
generate_acip_schema-0.0.2.dist-info/WHEEL
generate_acip_schema-0.0.2.dist-info/top_level.txt
generate_acip_schema-0.0.2.dist-info/RECORD
