Metadata-Version: 2.1
Name: generate-acip-schema
Version: 0.0.2
Summary: A small package mapping BDRC schema to ACIP's current Elasticsearch database
Home-page: https://github.com/joelcrawford/generate-acip-schema
Author: Joel Crawford
Author-email: joelrootcrawford@gmail.com
License: UNKNOWN
Platform: UNKNOWN
Classifier: Programming Language :: Python :: 3
Classifier: License :: OSI Approved :: MIT License
Classifier: Operating System :: OS Independent
Requires-Python: >=3.6
Requires-Dist: elasticsearch
Requires-Dist: gspread
Requires-Dist: oauth2client
